multimodalmaestro/__init__.py
multimodalmaestro/lmms/__init__.py
multimodalmaestro/lmms/gpt4.py
multimodalmaestro/markers/__init__.py
multimodalmaestro/markers/sam.py
multimodalmaestro/postprocessing/__init__.py
multimodalmaestro/postprocessing/mask.py
multimodalmaestro/postprocessing/text.py
multimodalmaestro/primitives.py
multimodalmaestro/visualizers.py
multimodal_maestro-0.1.0.dist-info/LICENSE
multimodal_maestro-0.1.0.dist-info/METADATA
multimodal_maestro-0.1.0.dist-info/WHEEL
multimodal_maestro-0.1.0.dist-info/RECORD
